README.rst
setup.py
best_templatetags/__init__.py
best_templatetags/settings.py
best_templatetags/urls.py
best_templatetags/wsgi.py
best_templatetags/templatetags/__init__.py
best_templatetags/templatetags/best_filters.py
best_templatetags/templatetags/best_tags.py
best_templatetags/tests/__init__.py
best_templatetags/tests/test_doctests.py
django_best_templatetags.egg-info/PKG-INFO
django_best_templatetags.egg-info/SOURCES.txt
django_best_templatetags.egg-info/dependency_links.txt
django_best_templatetags.egg-info/eager_resources.txt
django_best_templatetags.egg-info/not-zip-safe
django_best_templatetags.egg-info/requires.txt
django_best_templatetags.egg-info/top_level.txt